ansaotuvi_website/__init__.py
ansaotuvi_website/apps.py
ansaotuvi_website/tests.py
ansaotuvi_website/urls.py
ansaotuvi_website/utils.py
ansaotuvi_website/views.py
ansaotuvi_website/static/client.js
ansaotuvi_website/static/html2canvas.js
ansaotuvi_website/static/jquery.min.js
ansaotuvi_website/static/jsrender.min.js
ansaotuvi_website/static/lstv.js
ansaotuvi_website/static/simpleserver
ansaotuvi_website/static/style.css
ansaotuvi_website/static/texture.jpg
ansaotuvi_website/static/zebra_tooltips.js
ansaotuvi_website/templates/index.html
ansaotuvi_website-0.1.6.dist-info/LICENSE.md
ansaotuvi_website-0.1.6.dist-info/METADATA
ansaotuvi_website-0.1.6.dist-info/WHEEL
ansaotuvi_website-0.1.6.dist-info/top_level.txt
ansaotuvi_website-0.1.6.dist-info/RECORD
