Metadata-Version: 2.1
Name: ansaotuvi-website
Version: 0.1.6
Summary: A small example package
Home-page: https://github.com/hieudo-ursa/ansaotuvi-website
Author: hieu.do
Author-email: "hieu.do" <hieu.do@ursa.vn>
Project-URL: Homepage, https://github.com/hieudo-ursa/ansaotuvi-website
Project-URL: Issues, https://github.com/hieudo-ursa/ansaotuvi-website/issues
Classifier: Programming Language :: Python :: 3
Classifier: License :: OSI Approved :: MIT License
Classifier: Operating System :: OS Independent
Requires-Python: >=3.8
License-File: LICENSE.md
